src/__init__.py
src/ftp_server.py
turn_my_machine_ftp_server-1.0.0.dist-info/METADATA
turn_my_machine_ftp_server-1.0.0.dist-info/WHEEL
turn_my_machine_ftp_server-1.0.0.dist-info/top_level.txt
turn_my_machine_ftp_server-1.0.0.dist-info/RECORD
